rapidpro_expressions-1.8.dist-info/METADATA
rapidpro_expressions-1.8.dist-info/RECORD
rapidpro_expressions-1.8.dist-info/WHEEL
rapidpro_expressions-1.8.dist-info/top_level.txt
temba_expressions/__init__.py
temba_expressions/conversions.py
temba_expressions/dates.py
temba_expressions/evaluator.py
temba_expressions/month.aliases
temba_expressions/tests.py
temba_expressions/utils.py
temba_expressions/functions/__init__.py
temba_expressions/functions/custom.py
temba_expressions/functions/excel.py
temba_expressions/gen/ExcellentLexer.py
temba_expressions/gen/ExcellentParser.py
temba_expressions/gen/__init__.py
