Metadata-Version: 2.1
Name: rapidpro-expressions
Version: 1.8
Summary: Python implementation of the RapidPro expression and templating system
Home-page: https://github.com/rapidpro/expressions
Author: Nyaruka
Author-email: code@nyaruka.com
License: BSD
Keywords: rapidpro templating
Platform: UNKNOWN
Classifier: Development Status :: 5 - Production/Stable
Classifier: Intended Audience :: Developers
Classifier: Topic :: Software Development :: Libraries
Classifier: License :: OSI Approved :: BSD License
Classifier: Programming Language :: Python :: 3
Requires-Dist: antlr4-python3-runtime
Requires-Dist: python-dateutil
Requires-Dist: pytz
Requires-Dist: regex
Requires-Dist: iso8601
